cliapp/__init__.py
cliapp/application.py
cliapp/command.py
cliapp/interface.py
cliapp/config/__init__.py
cliapp/config/application.py
cliapp/config/base.py
cliapp/config/color.py
cliapp/config/shell.py
cliapp/config/theme.py
cliapp/config/version.py
cliapp/util/defaults.py
cliapp/util/synchronizer.py
cliapp/util/tools.py
dev_cliapp-1.0.0.dist-info/licenses/LICENSE
dev_cliapp-1.0.0.dist-info/METADATA
dev_cliapp-1.0.0.dist-info/WHEEL
dev_cliapp-1.0.0.dist-info/top_level.txt
dev_cliapp-1.0.0.dist-info/RECORD
