Metadata-Version: 2.4
Name: dev-cliapp
Version: 1.0.0
Summary: A modular package for building CLI applications
Author-email: Devin Green <devin.green@me.com>
License-Expression: MIT
Project-URL: Homepage, https://github.com/devingreen4/cliapp
Project-URL: Issues, https://github.com/devingreen4/cliapp/issues
Classifier: Programming Language :: Python :: 3
Classifier: Operating System :: OS Independent
Requires-Python: >=3.9
License-File: LICENSE
Requires-Dist: cmd2
Requires-Dist: pyfiglet
Requires-Dist: importlib-metadata; python_version < "3.10"
Dynamic: license-file
